hubspot/__init__.py
hubspot/client.py
hubspot/exceptions.py
hubspot/hubspot.py
hubspot/auth/__init__.py
hubspot/auth/oauth/__init__.py
hubspot/auth/oauth/api_client.py
hubspot/auth/oauth/configuration.py
hubspot/auth/oauth/exceptions.py
hubspot/auth/oauth/rest.py
hubspot/auth/oauth/api/__init__.py
hubspot/auth/oauth/api/access_tokens_api.py
hubspot/auth/oauth/api/refresh_tokens_api.py
hubspot/auth/oauth/api/tokens_api.py
hubspot/auth/oauth/models/__init__.py
hubspot/auth/oauth/models/access_token_info_response.py
hubspot/auth/oauth/models/error.py
hubspot/auth/oauth/models/error_detail.py
hubspot/auth/oauth/models/refresh_token_info_response.py
hubspot/auth/oauth/models/token_response_if.py
hubspot/automation/__init__.py
hubspot/automation/actions/__init__.py
hubspot/automation/actions/api_client.py
hubspot/automation/actions/configuration.py
hubspot/automation/actions/exceptions.py
hubspot/automation/actions/rest.py
hubspot/automation/actions/api/__init__.py
hubspot/automation/actions/api/callbacks_api.py
hubspot/automation/actions/api/definitions_api.py
hubspot/automation/actions/api/functions_api.py
hubspot/automation/actions/api/revisions_api.py
hubspot/automation/actions/models/__init__.py
hubspot/automation/actions/models/action_function.py
hubspot/automation/actions/models/action_function_identifier.py
hubspot/automation/actions/models/action_labels.py
hubspot/automation/actions/models/action_revision.py
hubspot/automation/actions/models/batch_input_callback_completion_batch_request.py
hubspot/automation/actions/models/callback_completion_batch_request.py
hubspot/automation/actions/models/callback_completion_request.py
hubspot/automation/actions/models/collection_response_action_function_identifier_no_paging.py
hubspot/automation/actions/models/collection_response_action_revision_forward_paging.py
hubspot/automation/actions/models/collection_response_extension_action_definition_forward_paging.py
hubspot_api_client-8.1.1.dist-info/LICENSE
hubspot_api_client-8.1.1.dist-info/METADATA
hubspot_api_client-8.1.1.dist-info/WHEEL
hubspot_api_client-8.1.1.dist-info/top_level.txt
hubspot_api_client-8.1.1.dist-info/RECORD
