Metadata-Version: 2.1
Name: hubspot-api-client
Version: 8.1.1
Summary: HubSpot API client
Home-page: https://github.com/HubSpot/hubspot-api-python
Author: HubSpot
Author-email: support@hubspot.com
License: Apache-2.0
Requires-Python: >=3.7
License-File: LICENSE
Requires-Dist: urllib3 >=1.15
Requires-Dist: six >=1.10
Requires-Dist: certifi
Requires-Dist: python-dateutil
Provides-Extra: dev
Requires-Dist: pytest ; extra == 'dev'
Requires-Dist: black ; extra == 'dev'
